Workbook

Sheet Resumo
B1: MAPA DE ACTIVIDADES
B2: FADA — Fundo de Apoio ao Desenvolvimento Agrário
B4: IDENTIFICAÇÃO
B5: Direcção | C5: DSG — Direcção de Serviços Gerais
B6: Período (mês/ano) | C6: Setembro de 2026
B7: Elaborado por
B8: Data de elaboração
B9: Aprovado por (responsável da DSG)
B11: RESUMO DO PERÍODO (calculado automaticamente)
B12: Categoria | C12: N.º de registos | D12: Quantidade de bens | E12: Valor (Kz) | F12: Quantidade de facturas
B13: Serviços adquiridos | C13: =COUNTA('Serviços Adquiridos'!B8:B1000) -> 0 | D13: — | E13: =SUM('Serviços Adquiridos'!E8:E1000) -> 0 | F13: =SUM('Serviços Adquiridos'!F8:F1000) -> 0
B14: Bens adquiridos | C14: =COUNTIF('Bens Adquiridos'!B8:B1000,"Bem") -> 0 | D14: =SUMIF('Bens Adquiridos'!B8:B1000,"Bem",'Bens Adquiridos'!D8:D1000) -> 0 | E14: =SUMIF('Bens Adquiridos'!B8:B1000,"Bem",'Bens Adquiridos'!F8:F1000) -> 0 | F14: =SUMIF('Bens Adquiridos'!B8:B1000,"Bem",'Bens Adquiridos'!G8:G1000) -> 0
B15: Imobilizados adquiridos | C15: =COUNTIF('Bens Adquiridos'!B8:B1000,"Imobilizado") -> 0 | D15: =SUMIF('Bens Adquiridos'!B8:B1000,"Imobilizado",'Bens Adquiridos'!D8:D1000) -> 0 | E15: =SUMIF('Bens Adquiridos'!B8:B1000,"Imobilizado",'Bens Adquiridos'!F8:F1000) -> 0 | F15: =SUMIF('Bens Adquiridos'!B8:B1000,"Imobilizado",'Bens Adquiridos'!G8:G1000) -> 0
B16: TOTAL GERAL | C16: =SUM(C13:C15) -> 0 | D16: =SUM(D14:D15) -> 0 | E16: =SUM(E13:E15) -> 0 | F16: =SUM(F13:F15) -> 0
B18: Células a amarelo: a preencher pelo utilizador. Os restantes valores são calculados a partir das folhas «Serviços Adquiridos» e «Bens Adquiridos» (linhas 8 a 1000). A linha de exemplo (linha 7) não entra nos totais. Os valores de exemplo em Identificação devem ser substituídos.

Sheet Serviços Adquiridos
A1: MAPA DE ACTIVIDADES — SERVIÇOS ADQUIRIDOS
A2: ="FADA — Fundo de Apoio ao Desenvolvimento Agrário | Direcção: "&Resumo!C5&" | Período: "&Resumo!C6 -> FADA — Fundo de Apoio ao Desenvolvimento Agrário | Direcção: DSG — Direcção de Serviços Gerais | Período: Setembro de 2026
B3: Campos do modelo | C3: Campos sugeridos (opcionais) | D3: Preencher a partir da linha 8. A linha 7 é apenas um exemplo e não entra nos totais.
B4: TOTAL | E4: =SUM(E8:E1000) -> 0 | F4: =SUM(F8:F1000) -> 0
A5: N.º | B5: Serviço | C5: Local prestado | D5: Objectivo/Motivo do Serviço | E5: Valor | F5: Quantidade de facturas de serviços | G5: Data do documento | H5: Fornecedor | I5: Tipo de documento | J5: N.º do documento | K5: Código do artigo | L5: Estado da aprovação | M5: Data da aprovação | N5: N.º da Nota de Pagamento (NP) | O5: Data do pagamento | P5: Observações
B6: Descrição do serviço adquirido | C6: Local onde o serviço foi prestado | D6: Finalidade ou razão da contratação | E6: Valor total em Kwanzas (Kz) | F6: N.º de facturas do serviço | G6: Data da factura (dd/mm/aaaa) | H6: Código/nome do fornecedor no Primavera | I6: VFAP ou VFA | J6: N.º do documento no Primavera | K6: Código do artigo (ex.: DSG0001) | L6: Estado do documento APR | M6: Data da aprovação (dd/mm/aaaa) | N6: N.º da NP gerada pela DFI | O6: Data do pagamento (dd/mm/aaaa) | P6: Informação adicional
A7: Ex. | B7: Manutenção de equipamentos informáticos | C7: Sede do FADA, Luanda | D7: Garantir a operacionalidade dos postos de trabalho | E7: 350000 | F7: 1 | G7: 15/09/2026 | H7: Informática & Serviços, Lda | I7: VFA — Factura | J7: VFA 2026/0112 | K7: DSG0001 | L7: Aprovado | M7: 16/09/2026 | N7: NP 2026/0045 | O7: 18/09/2026 | P7: Exemplo de preenchimento
A8: =IF(B8="","",ROW()-7)
A9: =IF(B9="","",ROW()-7)
A10: =IF(B10="","",ROW()-7)
A11: =IF(B11="","",ROW()-7)
A12: =IF(B12="","",ROW()-7)
A13: =IF(B13="","",ROW()-7)
A14: =IF(B14="","",ROW()-7)
A15: =IF(B15="","",ROW()-7)
A16: =IF(B16="","",ROW()-7)
A17: =IF(B17="","",ROW()-7)
A18: =IF(B18="","",ROW()-7)
A19: =IF(B19="","",ROW()-7)
... A57: =IF(B57="","",ROW()-7)

Sheet Bens Adquiridos
A1: MAPA DE ACTIVIDADES — BENS ADQUIRIDOS
A2: ="FADA — Fundo de Apoio ao Desenvolvimento Agrário | Direcção: "&Resumo!C5&" | Período: "&Resumo!C6 -> FADA — Fundo de Apoio ao Desenvolvimento Agrário | Direcção: DSG — Direcção de Serviços Gerais | Período: Setembro de 2026
B3: Campos do modelo | C3: Campos sugeridos (opcionais) | D3: Preencher a partir da linha 8. A linha 7 é apenas um exemplo e não entra nos totais.
B4: TOTAL | D4: =SUM(D8:D1000) -> 0 | F4: =SUM(F8:F1000) -> 0 | G4: =SUM(G8:G1000) -> 0
A5: N.º | B5: Bens/Imobilizados | C5: Nome do bem ou imobilizado | D5: Quantidade dos bens adquirido | E5: Centro de Custo | F5: Valor | G5: Quantidade de facturas de bens/imobilizados | H5: Data do documento | I5: Fornecedor | J5: Tipo de documento | K5: N.º do documento | L5: Código do artigo | M5: Estado da aprovação | N5: Data da aprovação | O5: N.º da Nota de Pagamento (NP) | P5: Data do pagamento | Q5: Localização / Responsável pelo bem | R5: Observações
B6: Seleccionar: Bem ou Imobilizado | C6: Designação do bem ou imobilizado | D6: N.º de unidades adquiridas | E6: Centro de custo imputado | F6: Valor total em Kwanzas (Kz) | G6: N.º de facturas dos bens | H6: Data da factura (dd/mm/aaaa) | I6: Código/nome do fornecedor no Primavera | J6: VFAP ou VFA | K6: N.º do documento no Primavera | L6: Código do artigo (ex.: DSG0001) | M6: Estado do documento APR | N6: Data da aprovação (dd/mm/aaaa) | O6: N.º da NP gerada pela DFI | P6: Data do pagamento (dd/mm/aaaa) | Q6: Onde está afecto e quem responde | R6: Informação adicional
A7: Ex. | B7: Bem | C7: Papel A4 (resma) | D7: 50 | E7: Direcção de Serviços Gerais | F7: 425000 | G7: 1 | H7: 15/09/2026 | I7: Papelaria Central, Lda | J7: VFA — Factura | K7: VFA 2026/0113 | L7: DSG0002 | M7: Aprovado | N7: 16/09/2026 | O7: NP 2026/0046 | P7: 18/09/2026 | Q7: Armazém da DSG | R7: Exemplo de preenchimento
A8: =IF(B8="","",ROW()-7)
A9: =IF(B9="","",ROW()-7)
A10: =IF(B10="","",ROW()-7)
A11: =IF(B11="","",ROW()-7)
A12: =IF(B12="","",ROW()-7)
A13: =IF(B13="","",ROW()-7)
A14: =IF(B14="","",ROW()-7)
A15: =IF(B15="","",ROW()-7)
A16: =IF(B16="","",ROW()-7)
A17: =IF(B17="","",ROW()-7)
A18: =IF(B18="","",ROW()-7)
A19: =IF(B19="","",ROW()-7)
... A57: =IF(B57="","",ROW()-7)

Sheet Guia de Preenchimento
A1: GUIA DE PREENCHIMENTO
A3: Folha | B3: Campo | C3: Tipo | D3: Como preencher | E3: Origem no Manual de Procedimentos / Primavera
A4: Serviços Adquiridos | B4: Serviço | C4: Modelo | D4: Descrição do serviço adquirido. | E4: Descrição do artigo/documento — Compras → Compras → Documentos (2.3.4 e 2.3.5).
A5: Serviços Adquiridos | B5: Local prestado | C5: Modelo | D5: Local onde o serviço foi efectivamente prestado. | E5: Descrições adicionais do processo (2.3.5).
A6: Serviços Adquiridos | B6: Objectivo/Motivo do Serviço | C6: Modelo | D6: Finalidade ou razão que justifica a contratação. | E6: Dossiê do processo anexado no Editor de Compras (2.3.7).
A7: Serviços Adquiridos | B7: Valor | C7: Modelo | D7: Valor total do serviço, em Kwanzas. | E7: Preço e quantidades do documento VFAP/VFA (2.3.6).
A8: Serviços Adquiridos | B8: Quantidade de facturas de serviços | C8: Modelo | D8: N.º de facturas (VFA) relativas ao serviço. | E8: Documentos registados em Compras → Compras → Documentos (2.3).
A9: Bens Adquiridos | B9: Bens/Imobilizados | C9: Modelo | D9: Seleccionar «Bem» ou «Imobilizado» na lista. | E9: Classificação do artigo — Marketing e Vendas → Inventários → Artigos (2.1).
A10: Bens Adquiridos | B10: Nome do bem ou imobilizado | C10: Modelo | D10: Designação do bem ou imobilizado. | E10: Artigo registado no sistema (2.1 e 2.3.4).
A11: Bens Adquiridos | B11: Quantidade dos bens adquirido | C11: Modelo | D11: N.º de unidades adquiridas. | E11: Quantidades do documento VFAP/VFA (2.3.6).
A12: Bens Adquiridos | B12: Centro de Custo | C12: Modelo | D12: Centro de custo a que o bem é imputado. | E12: Descrições adicionais do processo (2.3.5).
A13: Bens Adquiridos | B13: Valor | C13: Modelo | D13: Valor total, em Kwanzas. | E13: Preço e quantidades do documento (2.3.6).
A14: Bens Adquiridos | B14: Quantidade de facturas de bens/imobilizados | C14: Modelo | D14: N.º de facturas (VFA) dos bens e imobilizados. | E14: Documentos registados em Compras (2.3).
... A25: Ambas | B25: Observações | C25: Sugerido | D25: Informação adicional relevante. | E25: —

Sheet Listas
A1: Bens/Imobilizados | B1: Tipo de documento | C1: Estado da aprovação
A2: Bem | B2: VFAP — Factura Provisória | C2: Pendente
A3: Imobilizado | B3: VFA — Factura | C3: Aprovado
A6: Listas usadas nos menus pendentes. Os valores seguem o glossário do manual (VFAP, VFA); o estado de aprovação corresponde ao documento APR.
